mehdashti_errors/__init__.py
mehdashti_errors/exceptions.py
mehdashti_errors/handlers.py
mehdashti_errors/models.py
mehdashti_errors/py.typed
mehdashti_errors-0.2.0.dist-info/METADATA
mehdashti_errors-0.2.0.dist-info/WHEEL
mehdashti_errors-0.2.0.dist-info/RECORD
