Metadata-Version: 2.4
Name: mehdashti-errors
Version: 0.2.0
Summary: Standardized error handling for Smart Platform FastAPI services
Project-URL: Homepage, https://github.com/mehdashti/smart-platform
Project-URL: Repository, https://github.com/mehdashti/smart-platform.git
Project-URL: Issues, https://github.com/mehdashti/smart-platform/issues
Author: mehdashti
License: MIT
Keywords: api-errors,error-handling,exceptions,fastapi,validation
Classifier: Development Status :: 4 - Beta
Classifier: Framework :: FastAPI
Classifier: Intended Audience :: Developers
Classifier: License :: OSI Approved :: MIT License
Classifier: Programming Language :: Python :: 3
Classifier: Programming Language :: Python :: 3.13
Requires-Python: >=3.13
Requires-Dist: fastapi>=0.115.0
Requires-Dist: loguru>=0.7.2
Requires-Dist: mehdashti-observability>=0.2.0
Requires-Dist: pydantic>=2.10.0
Provides-Extra: dev
Requires-Dist: httpx>=0.27.0; extra == 'dev'
Requires-Dist: pytest-asyncio>=0.24.0; extra == 'dev'
Requires-Dist: pytest>=8.0.0; extra == 'dev'
